{
  "packages": [
    {
      "name": "telosair",
      "maintainer": "telosair",
      "websiteURL": "https://telosair.com",
      "email": "insights@telosair.com",
      "platforms": [
        {
          "name": "telosair Boards",
          "architecture": "telosair",
          "version": "1.0.5",
          "category": "Contributed",
          "url": "https://github.com/Potsdam-Sensors/ArduinoPackage/raw/refs/heads/main/telosairBoards.zip",
          "archiveFileName": "telosairBoards.zip",
          "checksum": "SHA-256:2a8c252ca437dd4cc3a3acf6412d870af72e63a744bdc1f691b6ce648d1cf893",
          "size": "1279339"
        }
        ],  
        "toolsDependencies": [
                   {
              "packager": "arduino",
              "name": "arm-none-eabi-gcc",
              "version": "4.8.3-2014q1"
            },
            {
              "packager": "arduino",
              "name": "bossac",
              "version": "1.8.0-48-gb176eee"
            },
            {
              "packager": "arduino",
              "name": "openocd",
              "version": "0.9.0-arduino"
            },
            {
              "packager": "arduino",
              "name": "CMSIS",
              "version": "4.5.0"
            },
            {
              "packager": "arduino",
              "name": "CMSIS-Atmel",
              "version": "1.2.0"
            }
			] 

    }   
]
}
